Metadata-Version: 1.0
Name: gaussian-binomialDis
Version: 1.0
Summary: Gaussian and Binomial distributions
Home-page: UNKNOWN
Author: Souilah Amine
Author-email: souilah.amine@gmail.com
License: UNKNOWN
Platform: UNKNOWN
